requmancer/__init__.py
requmancer/__main__.py
requmancer/main.py
requmancer-0.1.0.dist-info/LICENSE
requmancer-0.1.0.dist-info/METADATA
requmancer-0.1.0.dist-info/WHEEL
requmancer-0.1.0.dist-info/entry_points.txt
requmancer-0.1.0.dist-info/top_level.txt
requmancer-0.1.0.dist-info/RECORD
