Metadata-Version: 2.1
Name: requmancer
Version: 0.1.0
Summary: A tool to generate requirements files from Python projects
Home-page: https://github.com/ParisNeo/requmancer
Author: ParisNeo
Author-email: parisneoai@gmail.com
Classifier: Development Status :: 3 - Alpha
Classifier: Intended Audience :: Developers
Classifier: License :: OSI Approved :: MIT License
Classifier: Operating System :: OS Independent
Classifier: Programming Language :: Python :: 3
Classifier: Programming Language :: Python :: 3.6
Classifier: Programming Language :: Python :: 3.7
Classifier: Programming Language :: Python :: 3.8
Classifier: Programming Language :: Python :: 3.9
Requires-Python: >=3.6
License-File: LICENSE
Requires-Dist: setuptools >=58.0.0
Provides-Extra: dev
Requires-Dist: pytest >=6.2.4 ; extra == 'dev'
Requires-Dist: flake8 >=3.9.2 ; extra == 'dev'
Requires-Dist: black >=21.6b0 ; extra == 'dev'
Requires-Dist: twine >=3.4.1 ; extra == 'dev'
Requires-Dist: wheel >=0.37.0 ; extra == 'dev'
